caishen_sdk_py/__init__.py
caishen_sdk_py/caishen.py
caishen_sdk_py/cash/__init__.py
caishen_sdk_py/cash/cash_funcs.py
caishen_sdk_py/crypto/__init__.py
caishen_sdk_py/crypto/crypto_funcs.py
caishen_sdk_python/__init__.py
caishen_sdk_python/caishen.py
caishen_sdk_python/utils.py
caishen_sdk_python/adapters/__init__.py
caishen_sdk_python/agents/__init__.py
caishen_sdk_python/agents/tools.py
caishen_sdk_python/cash/__init__.py
caishen_sdk_python/cash/cash.py
caishen_sdk_python/cash/schema.py
caishen_sdk_python/constants/__init__.py
caishen_sdk_python/constants/app.py
caishen_sdk_python/constants/chain_ids.py
caishen_sdk_python/constants/chains.py
caishen_sdk_python/constants/public_rpc_endpoints.py
caishen_sdk_python/crypto/__init__.py
caishen_sdk_python/crypto/schema.py
caishen_sdk_python/crypto/send.py
caishen_sdk_python/crypto/swap.py
caishen_sdk_python/crypto/wallets.py
caishen_sdk_python/interfaces/__init__.py
caishen_sdk_python/tools/ToolBase.py
caishen_sdk_python/tools/__init__.py
caishen_sdk_python/tools/get_tools.py
caishen_sdk_python/tools/caishen/__init__.py
caishen_sdk_python/tools/caishen/cash/__init__.py
caishen_sdk_python/tools/caishen/cash/balance.py
caishen_sdk_python/tools/caishen/cash/deposit.py
caishen_sdk_python/tools/caishen/cash/get_supported_tokens.py
caishen_sdk_python/tools/caishen/cash/send.py
caishen_sdk_python/tools/caishen/cash/withdraw.py
caishen_sdk_python/tools/caishen/crypto/__init__.py
caishen_sdk_python/tools/caishen/crypto/balance.py
caishen_sdk_python/tools/caishen/crypto/balance_others.py
caishen_sdk_python/tools/caishen/crypto/get_chains.py
caishen_sdk_python/tools/caishen/crypto/get_rpc.py
caishen_sdk_python/tools/caishen/crypto/send.py
caishen_sdk_python/tools/caishen/crypto/swap.py
caishen_sdk_python/tools/caishen/crypto/swap_route.py
caishen_sdk_python/tools/interfaces/__init__.py
caishen_sdk_python-0.1.3.dist-info/METADATA
caishen_sdk_python-0.1.3.dist-info/WHEEL
caishen_sdk_python-0.1.3.dist-info/top_level.txt
caishen_sdk_python-0.1.3.dist-info/RECORD
